besta_tools/__init__.py
besta_tools/common/__init__.py
besta_tools/common/formats.py
besta_tools/common/utils.py
besta_tools/dfutool/__init__.py
besta_tools/dfutool/device.py
besta_tools/dfutool/dfu.py
besta_tools/dfutool/formats.py
besta_tools/dfutool/usbms_const.py
besta_tools/elf2bestape/__init__.py
besta_tools/elf2bestape/cli.py
besta_tools/elf2bestape/consts.py
besta_tools/elf2bestape/formats.py
besta_tools/elf2bestape/steps/__init__.py
besta_tools/elf2bestape/steps/complete_headers.py
besta_tools/elf2bestape/steps/generate_sections.py
besta_tools/elf2bestape/steps/initialize.py
besta_tools/elf2bestape/steps/scan_segments.py
besta_tools/elf2bestape/steps/serialize.py
besta_tools/elf2bestape/utils.py
besta_tools/imgtool/__init__.py
besta_tools/imgtool/formats.py
besta_tools/romtool/__init__.py
besta_tools/romtool/builder.py
besta_tools/romtool/formats.py
besta_tools/titlemgr/__init__.py
besta_tools-1.0.2.dist-info/METADATA
besta_tools-1.0.2.dist-info/WHEEL
besta_tools-1.0.2.dist-info/entry_points.txt
besta_tools-1.0.2.dist-info/RECORD
