Metadata-Version: 2.3
Name: besta-tools
Version: 1.0.2
Summary: Tools for working with Besta data formats
License: MIT
Author: dogtopus
Author-email: dogtopus@users.noreply.github.com
Requires-Python: >=3.12,<4.0
Classifier: License :: OSI Approved :: MIT License
Classifier: Programming Language :: Python :: 3
Classifier: Programming Language :: Python :: 3.12
Classifier: Programming Language :: Python :: 3.13
Requires-Dist: click (>=8.1.7,<9.0.0)
Requires-Dist: construct-typing (>=0.6.2,<0.7.0)
Requires-Dist: libusb-package (>=1.0.26.3,<2.0.0.0)
Requires-Dist: marshmallow-dataclass (>=8.7.0,<9.0.0)
Requires-Dist: pefile (>=2024.8.26,<2025.0.0)
Requires-Dist: pyelftools (>=0.32,<0.33)
Requires-Dist: pyusb (>=1.2.1,<2.0.0)
Requires-Dist: pyyaml (>=6.0.1,<7.0.0)
